example_pkg/__init__.py
yxxhero-0.0.8.dist-info/METADATA
yxxhero-0.0.8.dist-info/WHEEL
yxxhero-0.0.8.dist-info/entry_points.txt
yxxhero-0.0.8.dist-info/top_level.txt
yxxhero-0.0.8.dist-info/RECORD
