Metadata-Version: 2.1
Name: yxxhero
Version: 0.0.8
Summary: get a chinesename by random
Home-page: https://github.com/mouday/chinesename
Author: Peng Shiyu
Author-email: pengshiyuyx@gmail.com
License: MIT License
Platform: UNKNOWN
Classifier: Programming Language :: Python :: 3
Classifier: License :: OSI Approved :: MIT License
Classifier: Operating System :: OS Independent
